rammer.py
rammer-1.0.0.dist-info/WHEEL
rammer-1.0.0.dist-info/METADATA
rammer-1.0.0.dist-info/RECORD
